oh_download.py
open_humans_downloader-1.0.1.dist-info/DESCRIPTION.rst
open_humans_downloader-1.0.1.dist-info/METADATA
open_humans_downloader-1.0.1.dist-info/RECORD
open_humans_downloader-1.0.1.dist-info/WHEEL
open_humans_downloader-1.0.1.dist-info/entry_points.txt
open_humans_downloader-1.0.1.dist-info/metadata.json
open_humans_downloader-1.0.1.dist-info/top_level.txt
