Metadata-Version: 2.0
Name: open-humans-downloader
Version: 1.0.1
Summary: Download public member data from Open Humans
Home-page: https://github.com/PersonalGenomesOrg/open-humans-downloader
Author: Beau Gunderson
Author-email: beau@personalgenomes.org
License: MIT
Keywords: open-humans
Platform: UNKNOWN
Classifier: Environment :: Console
Classifier: Development Status :: 4 - Beta
Classifier: Intended Audience :: Developers
Classifier: Intended Audience :: End Users/Desktop
Classifier: Intended Audience :: Information Technology
Classifier: Intended Audience :: System Administrators
Classifier: License :: OSI Approved :: BSD License
Classifier: Operating System :: POSIX
Classifier: Operating System :: MacOS :: MacOS X
Classifier: Operating System :: Microsoft :: Windows
Classifier: Programming Language :: Python
Classifier: Topic :: Utilities
Requires-Dist: click (>=6.3)
Requires-Dist: humanfriendly (>=1.44.3)
Requires-Dist: requests (>=2.9.1)
Requires-Dist: tomorrow (>=0.2.4)
